{
    "navHome": "హోమ్",
    "navMarket": "మార్కెట్",
    "navCrops": "పంటలు",
    "navAIChat": "AI చాట్",
    "navProfile": "ప్రొఫైల్",
    "navLogout": "లాగ్ అవుట్",
    "currentWeather": "ప్రస్తుత వాతావరణం",
    "loadingWeather": "వాతావరణం లోడ్ అవుతోంది...",
    "kharifSeason": "ఖరీఫ్ సీజన్",
    "kharifDescription": "వర్షాకాలం ప్రారంభంలో (జూన్-జూలై) విత్తే పంటలు. ప్రధాన పంటలలో వరి, మొక్కజొన్న మరియు పత్తి ఉన్నాయి.",
    "rabiSeason": "రబీ సీజన్",
    "rabiDescription": "శీతాకాలంలో అక్టోబర్-డిసెంబర్‌లో విత్తే పంటలు. ప్రధాన పంటలలో గోధుమ, బార్లీ మరియు ఆవాలు ఉన్నాయి.",
    "zaidSeason": "జైద్ సీజన్",
    "zaidDescription": "రబీ మరియు ఖరీఫ్ సీజన్‌ల మధ్య (మార్చి-జూన్) పండించే వేసవి పంటలు.",
    "fruitIrrigation": "పండ్ల నీటిపారుదల",
    "fruitIrrigationDescription": "డ్రిప్ ఇరిగేషన్ పండ్ల తోటలకు అత్యంత సమర్థవంతమైనది, ఇది నేరుగా వేరు மண்டలానికి నీటిని అందిస్తుంది.",
    "language": "భాష",
    "selectLanguage": "మీకు ఇష్టమైన భాషను ఎంచుకోండి.",
    "marketTitle": "నేటి పంట మార్కెట్",
    "fetchingMarketPrices": "స్థానిక మార్కెట్ ధరలను పొందడానికి మీ స్థానం తిరిగి పొందబడుతోంది...",
    "addCropDetails": "కొత్త పంట వివరాలను జోడించండి",
    "cropName": "పంట పేరు",
    "variety": "రకం",
    "sowingDate": "విత్తే తేదీ",
    "harvestDate": "అपेक्षित కోత తేదీ",
    "landArea": "భూమి విస్తీర్ణం (ఎకరాలలో)",
    "soilType": "నేల రకం",
    "irrigationMethod": "నీటిపారుదల పద్ధతి",
    "getAIFeedback": "AI అభిప్రాయం పొందండి",
    "aiFeedback": "AI అభిప్రాయం",
    "aiAgriAssistant": "AI कृषि-సహాయకుడు",
    "aiWelcome": "నమస్కారం! ఈ రోజు మీ వ్యవసాయ ప్రశ్నలతో నేను మీకు ఎలా సహాయపడగలను?",
    "typeYourQuestion": "మీ ప్రశ్నను టైప్ చేయండి లేదా మైక్‌ని ఉపయోగించండి...",
    "profileInformation": "ప్రొఫైల్ సమాచారం",
    "username": "వినియోగదారు పేరు",
    "email": "ఇమెయిల్",
    "mobile": "మొబైల్",
    "changePassword": "పాస్‌వర్డ్ మార్చండి",
    "currentPassword": "ప్రస్తుత పాస్‌వర్డ్",
    "newPassword": "కొత్త పాస్‌వర్డ్",
    "updatePassword": "పాస్‌వర్డ్ నవీకరించండి",
    "dangerZone": "ప్రమాదకరమైన జోన్",
    "deleteAccountWarning": "మీ ఖాతాను తొలగించడం శాశ్వత చర్య మరియు దానిని రద్దు చేయడం సాధ్యం కాదు.",
    "deleteMyAccount": "నా ఖాతాను తొలగించు",
    "notSet": "సెట్ చేయబడలేదు",
    "changeLanguage": "మార్చు"
}